Metadata-Version: 2.4
Name: mcp-python-code-interpreter
Version: 1.1
Summary: MCP server for Python code execution and environment management
Author-email: YZFly <ethereal_ai@hotmail.com>
Project-URL: Homepage, https://github.com/yzfly/mcp-python-interpreter
Project-URL: Bug Tracker, https://github.com/yzfly/mcp-python-interpreter/issues
Classifier: Programming Language :: Python :: 3
Classifier: License :: OSI Approved :: MIT License
Classifier: Operating System :: OS Independent
Requires-Python: >=3.10
License-File: LICENSE
Requires-Dist: fastmcp>=2.11.3
Requires-Dist: mcp[cli]>=1.6.0
Dynamic: license-file
